[{"price":{"wat":"LINKUSD","val":"7826760000000000000","age":1664981831,"v":"1b","r":"3e51b8284d881e9e2a460bc01f4dbe79e796a0635e887b374a3225b1c7f7988d","s":"77be8820e3b55a0ecb842fbf19aa226372893a940dc46513b7920cf85e48468c","stark_r":"0x0","stark_s":"0x0","stark_pk":"0x0"},"trace":{"BTC/USD@binance_us":"19892.78","BTC/USD@bitstamp":"19892","BTC/USD@coinbasepro":"19890.44","BTC/USD@ftx":"19892","BTC/USD@gemini":"19890.3","BTC/USD@kraken":"19885.9","ETH/BTC@binance":"0.066624","ETH/USD@bitstamp":"1324.9","ETH/USD@coinbasepro":"1325.13","ETH/USD@ftx":"1325.1","ETH/USD@gemini":"1325.22","ETH/USD@kraken":"1325.59","ETH/USD@uniswapV3":"1325.0789259646594","LINK/BTC@binance":"0.0003933","LINK/ETH@uniswapV3":"0.005889910115669255","LINK/USD@bitstamp":"7.83","LINK/USD@coinbasepro":"7.824","LINK/USD@ftx":"7.8315","LINK/USD@gemini":"7.82697","LINK/USD@kraken":"7.82676"}},{"price":{"wat":"LINKUSD","val":"7828500000000000000","age":1664981830,"v":"1c","r":"9afdd032de4fff4a781d8cb4beb1f7db9c657803d8c8df2498302e7b0cf1c209","s":"73a81c911ed2f15329251abed2e676ec86d9029dbfbfe6980c7e44a5c8488a2b","stark_r":"0x0","stark_s":"0x0","stark_pk":"0x0"},"trace":{"BTC/USD@binance_us":"19915.09","BTC/USD@bitstamp":"19908","BTC/USD@coinbasepro":"19908.52","BTC/USD@ftx":"19906","BTC/USD@gemini":"19905.41","BTC/USD@kraken":"19912.9","ETH/BTC@binance":"0.066559","ETH/USD@bitstamp":"1325.5","ETH/USD@coinbasepro":"1325.01","ETH/USD@ftx":"1325.2","ETH/USD@gemini":"1324.59","ETH/USD@kraken":"1325.52","ETH/USD@uniswapV3":"1325.1119029480426","LINK/BTC@binance":"0.0003933","LINK/ETH@uniswapV3":"0.005889910115669255","LINK/USD@bitstamp":"7.83","LINK/USD@coinbasepro":"7.834","LINK/USD@ftx":"7.8285","LINK/USD@gemini":"7.82697","LINK/USD@kraken":"7.82697"}},{"price":{"wat":"MATICUSD","val":"833210415000000000","age":1664981837,"v":"1c","r":"d4c223a91cee44bc2eef0427e47f5c70a264ec7abc67e3d167b9598d00024752","s":"065a914973b76734893c9a4e9240a30d3f8aaa514e44b011960d184a53786320","stark_r":"0x0","stark_s":"0x0","stark_pk":"0x0"},"trace":{"maticusd@binance":"0.8332208300","maticusd@coinbase":"0.8332000000","maticusd@ftx":"0.8334610000","maticusd@gemini":"0.8330600000","maticusd@huobi":"0.8329628236","maticusd@kraken":"0.8333000000"}},{"price":{"wat":"ETHUSD","val":"1325100000000000000000","age":1664981827,"v":"1c","r":"edde8eede4658731975cc705534d424688bc6162ef5d9df2d979e3d355ea85a0","s":"3dac136cb11028dff8124d6aabd2d1e6a1cd6c421223f26e043432c54cd0c799","stark_r":"0x0","stark_s":"0x0","stark_pk":"0x0"},"trace":{"ethusd@binance":"1325.3081088000","ethusd@bitstamp":"1325.1000000000","ethusd@coinbase":"1324.9500000000","ethusd@ftx":"1325.0000000000","ethusd@gemini":"1324.5900000000","ethusd@kraken":"1325.5200000000","ethusd@uniswap_v3":"1325.1957441282"}},{"price":{"wat":"UNIUSD","val":"6548000000000000000","age":1664981826,"v":"1c","r":"acc9881f84a845479a915db60f78fbe326c0e9326daa7a2b8e97f30c999b556e","s":"1ef65c9f0808293e8cd7d3114798e323d459b2598d361e4a84df792ea68b1c11","stark_r":"0x7982828ce3085a856ec2f67ae5eaf76086f61368f1c98b903090c677c6f41c9","stark_s":"0x1448ffd52610919e295ce445e08c3e234dd977731b44fefe6061e173ec5ffee","stark_pk":"0x4c2413c39a3ca1ed66adaee5c24b0e830fd884ad6048408c6e2cc0fc429771f"},"trace":{"BTC/USD@bitstamp":"19908","BTC/USD@coinbasepro":"19901.13","BTC/USD@gemini":"19910.13","BTC/USD@kraken":"19902.1","BTC/USDT@binance":"19895.21","ETH/BTC@binance":"0.066559","ETH/USD@bitstamp":"1324.9","ETH/USD@coinbasepro":"1324.13","ETH/USD@ftx":"1325","ETH/USD@gemini":"1324.78","ETH/USD@kraken":"1325.51","ETH/USD@uniswapV3":"1325.1957441281588","ETH/USDT@ftx":"1325.1","ETH/USDT@huobi":"1324.9050000000002","UNI/BTC@binance":"0.0003291","UNI/ETH@uniswapV3":"0.004927645125242119","UNI/USD@coinbasepro":"6.547","UNI/USD@ftx":"6.548","UNI/USDT@huobi":"6.5492","USDT/USD@bitfinex":"1.0001","USDT/USD@kraken":"1.0001"}},{"price":{"wat":"ETHUSD","val":"1325015238000000000000","age":1664981827,"v":"1c","r":"4d4a6af6a17bcab2cdecf57baec78d96e7166680324267b4d1d2d67df3d1198d","s":"7b697d1e52773ac75b3bc3c8a40c74d7c8bfde63acc4188d7ef13373554b682a","stark_r":"0x0","stark_s":"0x0","stark_pk":"0x0"},"trace":{"BTC/USD@binance_us":"19907.07","BTC/USD@bitstamp":"19902","BTC/USD@coinbasepro":"19908.35","BTC/USD@ftx":"19890","BTC/USD@gemini":"19890.3","BTC/USD@kraken":"19900.2","ETH/BTC@binance":"0.06658","ETH/USD@bitstamp":"1324.9","ETH/USD@coinbasepro":"1324.92","ETH/USD@ftx":"1324.9","ETH/USD@gemini":"1325.22","ETH/USD@kraken":"1325.59","ETH/USD@uniswapV3":"1325.0789259646594"}},{"price":{"wat":"YFIUSD","val":"8150163775411363000000","age":1664981838,"v":"1c","r":"aa49861108bf25e9d1bfbdb9ad5da02ede64f02e0ab81aca1ef15a6eafc49995","s":"1cc93d04bc573ec70c4312e3234f7f1be063bd6b6137b89d1bb37c21b075a408","stark_r":"0x0","stark_s":"0x0","stark_pk":"0x0"},"trace":{"BTC/USD@binance_us":"19908.9","BTC/USD@bitstamp":"19908","BTC/USD@coinbasepro":"19905.3","BTC/USD@ftx":"19913","BTC/USD@gemini":"19910.13","BTC/USD@kraken":"19912.9","BTC/USDT@binance":"19905.82","BTC/USDT@okx":"19905","ETH/BTC@binance":"0.06656","ETH/USD@bitstamp":"1325.1","ETH/USD@coinbasepro":"1325.08","ETH/USD@ftx":"1325.2","ETH/USD@gemini":"1324.59","ETH/USD@kraken":"1325.52","ETH/USD@uniswapV3":"1325.1957441281588","ETH/YFI@balancerV2":"0.16335982431716056","USDT/USD@bitfinex":"1.0001","USDT/USD@coinbasepro":"1.00007","USDT/USD@ftx":"1.0002","USDT/USD@kraken":"1.0001","YFI/ETH@sushiswap":"6.162616076234956","YFI/USD@coinbasepro":"8148.19","YFI/USD@ftx":"8140","YFI/USD@kraken":"8152","YFI/USDT@binance":"8149","YFI/USDT@okx":"8154"}},{"price":{"wat":"MANAUSD","val":"693265000000000000","age":1664981833,"v":"1c","r":"5f17ca31941642d3af8d386bb8ee3290d1319da1505dfb592ef0d044c3ef718f","s":"7ef3cc2fdfe7eb132aafeb6dd0debdd0bc4362067c62278fe5639d4c345f5e66","stark_r":"0x0","stark_s":"0x0","stark_pk":"0x0"},"trace":{"BTC/USD@binance_us":"19915.09","BTC/USD@bitstamp":"19908","BTC/USD@coinbasepro":"19908.52","BTC/USD@ftx":"19906","BTC/USD@gemini":"19905.41","BTC/USD@kraken":"19912.9","BTC/USDT@binance":"19906.77","BTC/USDT@okx":"19907.5","MANA/BTC@binance":"3.483e-05","MANA/KRW@upbit":"994","MANA/USD@binance_us":"0.6935","MANA/USD@coinbasepro":"0.693","MANA/USD@ftx":"0.6932","MANA/USD@kraken":"0.69333","MANA/USDT@okx":"0.693","USDT/USD@bitfinex":"1.0001","USDT/USD@coinbasepro":"1.00007","USDT/USD@ftx":"1.0002","USDT/USD@kraken":"1.0001"}},{"price":{"wat":"FILUSD","val":"5479885857200000000","age":1664981830,"v":"1c","r":"21c58021a462dc1f0b052b775c9a7a99fc144636fea3ea949c3927e08d26a218","s":"535cef6a1fd5607602e9079537623c3297cc7f44c6e6574bbf3e98191eeb6f38","stark_r":"0x17225b635962bf638bc29df77d3842078ff83ac9252c52882629b0fd529e5c7","stark_s":"0x1b14226c691d0a5657dad57e0e69b1b8296cd36d62592ec3703bb3a393eebdd","stark_pk":"0x26cd35ce61b798e2e80d1d4d1f7d3f40f60dd19f2533e557808c1f5675471e9"},"trace":{"binance":"5.4706847056","coinbase":"5.4810000000","gemini":"5.4760000000","huobi":"5.4798858572","kraken":"5.4800000000"}},{"price":{"wat":"BTCUSD","val":"19909065000000002000000","age":1664981834,"v":"1c","r":"103079c9903a3eeb0eb7fdfefe8c587f22c61ef1ae8ca44b70da74b0527beea5","s":"62e9b946fa6270aa24767feb653f73e22475b900cb5205341c323ec1b768fa39","stark_r":"0xc9fe3f02d8c11e4dc2bc61139704b412a8d3abeffe3d787fde748ad076c477","stark_s":"0x6f49999f968aa625bacd244b6d0cb5caa8b6390755d01a63a39d32e114a77d8","stark_pk":"0x2dacd0e8df86be8df0b2bc5fcecb9ac14fa640fc4caf87efe5de013c44faeac"},"trace":{"BTC/USD@binance_us":"19899.18","BTC/USD@bitstamp":"19908","BTC/USD@coinbasepro":"19899.23","BTC/USD@ftx":"19913","BTC/USD@gemini":"19910.13","BTC/USD@kraken":"19912.8"}},{"price":{"wat":"WSTETHUSD","val":"1436220965203337500000","age":1664981830,"v":"1c","r":"27560128c552e3ea36dfac77eec47a5c499fec13ee51046ec7f5fbca8dd4d342","s":"011522470abbaa5dee44249af1ad9df7b55b32c3371cf8763e529405c4fdbc7d","stark_r":"0x46a5a8fe5861c348ac9155193d61f8f107bcbcb595d4328f3bae8ab558e25b6","stark_s":"0x109ecf8f971d8031271aa94339409c802f37138a6e928cdc0216c29d418ba80","stark_pk":"0x4d54d72263f75f14c4fd62a038b3e63d72f04ca55c5fc261224659f8525d058"},"trace":{"BTC/USD@binance_us":"19915.12","BTC/USD@bitstamp":"19904","BTC/USD@coinbasepro":"19913.64","BTC/USD@ftx":"19908","BTC/USD@gemini":"19905.41","BTC/USD@kraken":"19912.2","ETH/BTC@binance":"0.066576","ETH/USD@bitstamp":"1325.5","ETH/USD@coinbasepro":"1325.25","ETH/USD@ftx":"1325","ETH/USD@gemini":"1324.59","ETH/USD@kraken":"1325.52","ETH/USD@uniswapV3":"1325.1119029480426","STETH/ETH@balancerV2":"0.9955101098295706","STETH/ETH@curve":"0.995105970691631","WSTETH/STETH@wsteth":"1.088844688069204"}},{"price":{"wat":"ETHBTC","val":"66568000000000000","age":1664981834,"v":"1b","r":"12d3d77268ebe3e6a04c914faa45da750f1134bd9b31215629636f6e980f0bc5","s":"0c660e8261c7cd324ecf8d4a0194f0e9411c1754fd6d8f6c139d1e2839a7c0c7","stark_r":"0x0","stark_s":"0x0","stark_pk":"0x0"},"trace":{"ethbtc@binance":"0.0665460000","ethbtc@bitfinex":"0.0665950000","ethbtc@coinbase":"0.0665700000","ethbtc@huobi":"0.0665660000","ethbtc@kraken":"0.0666600000","ethbtc@poloniex":"0.0665500000"}},{"price":{"wat":"MANAUSD","val":"693209017000000000","age":1664981837,"v":"1c","r":"3d4a091a69a7dd6d1e957fcd5f73b851f926126eccf9b81bf867235179a1842f","s":"17309a87e4bb4134ad5e3f61646e05e1907cbdb23cc1b3041c7829433069a8fb","stark_r":"0x0","stark_s":"0x0","stark_pk":"0x0"},"trace":{"BTC/USD@binance_us":"19892.78","BTC/USD@bitstamp":"19892","BTC/USD@coinbasepro":"19890.44","BTC/USD@ftx":"19892","BTC/USD@gemini":"19890.3","BTC/USD@kraken":"19885.9","BTC/USDT@binance":"19887.85","BTC/USDT@okx":"19889","KRW/USD@openexchangerates":"0.000703","MANA/BTC@binance":"3.485e-05","MANA/KRW@upbit":"994","MANA/USD@binance_us":"0.6935","MANA/USD@coinbasepro":"0.6927","MANA/USD@ftx":"0.6932","MANA/USD@kraken":"0.69333","MANA/USDT@okx":"0.6928","USDT/USD@bitfinex":"1.0001","USDT/USD@coinbasepro":"1.00004","USDT/USD@ftx":"1.0002","USDT/USD@kraken":"1.0001"}},{"price":{"wat":"LINKUSD","val":"7825260000000000000","age":1664981835,"v":"1b","r":"8102075e02100d7cbe09d9bb857ec5457707a89957e31a1d27d05c3d8154ce29","s":"5d1bc4a8988467ba6f77d806ea3bac8a00c5cf4bf5500da474243cefbbf46bca","stark_r":"0x5b7e05b4caa103df7ad28f52a166fbb15361f8c33bb3834064b64321bc49b10","stark_s":"0x3a64014b87fcc2a44e4f548bf220f42fcb170030f3df11c3a86612c2d022004","stark_pk":"0x4d54d72263f75f14c4fd62a038b3e63d72f04ca55c5fc261224659f8525d058"},"trace":{"BTC/USD@binance_us":"19915.12","BTC/USD@bitstamp":"19904","BTC/USD@coinbasepro":"19913.64","BTC/USD@ftx":"19908","BTC/USD@gemini":"19905.41","BTC/USD@kraken":"19912.2","ETH/BTC@binance":"0.066576","ETH/USD@bitstamp":"1325.5","ETH/USD@coinbasepro":"1325.25","ETH/USD@ftx":"1325","ETH/USD@gemini":"1324.59","ETH/USD@kraken":"1325.52","ETH/USD@uniswapV3":"1325.1119029480426","LINK/BTC@binance":"0.0003933","LINK/ETH@uniswapV3":"0.005889910115669255","LINK/USD@bitstamp":"7.83","LINK/USD@coinbasepro":"7.822","LINK/USD@ftx":"7.8245","LINK/USD@gemini":"7.82697","LINK/USD@kraken":"7.82526"}},{"price":{"wat":"MATICUSD","val":"833709524063253900","age":1664981835,"v":"1c","r":"af975c6775d183ee870ccb97e462d380b45cc182cbf72020d41365919276df62","s":"1fec492745d6543461aef12c83a7a1d08e588be3977ccafd5d17f1bd36423064","stark_r":"0x0","stark_s":"0x0","stark_pk":"0x0"},"trace":{"BTC/USD@binance_us":"19908.9","BTC/USD@bitstamp":"19908","BTC/USD@coinbasepro":"19905.3","BTC/USD@ftx":"19913","BTC/USD@gemini":"19910.13","BTC/USD@kraken":"19912.9","BTC/USDT@binance":"19905.82","BTC/USDT@okx":"19905","MATIC/USD@coinbasepro":"0.8337","MATIC/USD@ftx":"0.833902","MATIC/USD@gemini":"0.83395","MATIC/USD@kraken":"0.8333","MATIC/USDT@binance":"0.8336","MATIC/USDT@huobi":"0.833535","USDT/USD@bitfinex":"1.0001","USDT/USD@coinbasepro":"1.00007","USDT/USD@ftx":"1.0002","USDT/USD@kraken":"1.0001"}},{"price":{"wat":"YFIUSD","val":"8149917133279500000000","age":1664981830,"v":"1b","r":"a1daaa881f47316a4fea415d4a3b700aad5dbf1e61e20598f82978c5d6794255","s":"405879c017751e7f21121280ea7cba151fac07c4100de338d7304aae494a18c3","stark_r":"0x0","stark_s":"0x0","stark_pk":"0x0"},"trace":{"yfiusd@balancer_v2":"8109.6914353133","yfiusd@binance":"8149.9171332795","yfiusd@coinbase":"8148.1900000000","yfiusd@ftx":"8140.0000000000","yfiusd@kraken":"8152.0000000000","yfiusd@okx":"8151.9173583705","yfiusd@sushiswap":"8164.2200226295"}},{"price":{"wat":"UNIUSD","val":"6547665976250000000","age":1664981830,"v":"1c","r":"97ecab3a8288beee9acbab53643ae86993d7ba6e47ac1e7b6faabea2bb9763f0","s":"3f5f3641fc0dfa2e95723ac959200480a8a5b852dacbb274edd7aea29ebb4a7e","stark_r":"0x4e2091ef7e7c5f321478fda19870f5a781d0b4d20b600f7f3c3c4b6b9e5cfcd","stark_s":"0x5a0aa1bdcde12cceade9a6fddbfac918eef6d1cc0eb2924b28018c89b67666a","stark_pk":"0x2dacd0e8df86be8df0b2bc5fcecb9ac14fa640fc4caf87efe5de013c44faeac"},"trace":{"BTC/USD@binance_us":"19899.18","BTC/USD@bitstamp":"19908","BTC/USD@coinbasepro":"19899.23","BTC/USD@ftx":"19913","BTC/USD@gemini":"19910.13","BTC/USD@kraken":"19912.8","BTC/USDT@binance":"19893.52","BTC/USDT@okx":"19897.6","ETH/BTC@binance":"0.066563","ETH/USD@bitstamp":"1324.9","ETH/USD@coinbasepro":"1324.29","ETH/USD@ftx":"1325.2","ETH/USD@gemini":"1324.78","ETH/USD@kraken":"1325.51","ETH/USD@uniswapV3":"1325.1957441281588","UNI/BTC@binance":"0.0003291","UNI/ETH@uniswapV3":"0.004927645125242119","UNI/USD@coinbasepro":"6.547","UNI/USD@ftx":"6.548","UNI/USDT@huobi":"6.54635","UNI/USDT@okx":"6.549","USDT/USD@bitfinex":"1.0001","USDT/USD@coinbasepro":"1.00007","USDT/USD@ftx":"1.0002","USDT/USD@kraken":"1.0001"}},{"price":{"wat":"WSTETHUSD","val":"1436071304474227000000","age":1664981828,"v":"1b","r":"3858df92e77efd31ec0f592d8ce8957baeef742a53020ad89e2d1cdc46aeb1a5","s":"26494c4cacc1c0bf037a964a427f0481547bfaf0a62ae5db99f7201351e40112","stark_r":"0x0","stark_s":"0x0","stark_pk":"0x0"},"trace":{"BTC/USD@binance_us":"19915.09","BTC/USD@bitstamp":"19908","BTC/USD@coinbasepro":"19908.52","BTC/USD@ftx":"19906","BTC/USD@gemini":"19905.41","BTC/USD@kraken":"19912.9","ETH/BTC@binance":"0.066559","ETH/USD@bitstamp":"1325.5","ETH/USD@coinbasepro":"1325.01","ETH/USD@ftx":"1325.2","ETH/USD@gemini":"1324.59","ETH/USD@kraken":"1325.52","ETH/USD@uniswapV3":"1325.1119029480426","STETH/ETH@balancerV2":"0.9955101098295706","STETH/ETH@curve":"0.995105970691631","WSTETH/STETH@wsteth":"1.088844688069204"}},{"price":{"wat":"MATICUSD","val":"833590349157500000","age":1664981838,"v":"1b","r":"cf290d8e7fb60f677817b79a4085727ece06394902b69558fece2d6a7ed1b502","s":"3cf88ed97a881b8b9d6921d89d37f3c1502e2ea4e0c47b543608e87389f7fefc","stark_r":"0x0","stark_s":"0x0","stark_pk":"0x0"},"trace":{"BTC/USD@binance_us":"19915.12","BTC/USD@bitstamp":"19904","BTC/USD@coinbasepro":"19907.99","BTC/USD@ftx":"19908","BTC/USD@gemini":"19905.41","BTC/USD@kraken":"19912.2","BTC/USDT@binance":"19912.01","BTC/USDT@okx":"19912.5","MATIC/USD@coinbasepro":"0.8339","MATIC/USD@ftx":"0.833393","MATIC/USD@gemini":"0.83441","MATIC/USD@kraken":"0.8333","MATIC/USDT@binance":"0.8337","MATIC/USDT@huobi":"0.833339","USDT/USD@bitfinex":"1.0001","USDT/USD@coinbasepro":"1.00007","USDT/USD@ftx":"1.0002","USDT/USD@kraken":"1.0001"}},{"price":{"wat":"BTCUSD","val":"19905050000000000000000","age":1664981833,"v":"1b","r":"fbe173ce37485d05e1a8196194923a8264c6fb6086b52bbcf06c3b2c7e106541","s":"276bd33a121f7ea480751cfdc9a11654f774fdeac8eaaaade8cb412e40d083ca","stark_r":"0x3877a8510afd06eb27b4ed913741e464d0a4adb7d1168a09a5d416dab003a74","stark_s":"0x1428cc8af31f285804f81ed1f1fcdb3d5487cf27115fb6497cff40aba60d285","stark_pk":"0x4c2413c39a3ca1ed66adaee5c24b0e830fd884ad6048408c6e2cc0fc429771f"},"trace":{"BTC/USD@bitstamp":"19908","BTC/USD@coinbasepro":"19901.13","BTC/USD@gemini":"19910.13","BTC/USD@kraken":"19902.1"}},{"price":{"wat":"BTCUSD","val":"19910100000000000000000","age":1664981825,"v":"1b","r":"8198481a0edf346e839d96b8409d0ea75084b67bc114c7744089f4a00ec60b8a","s":"5e435c6ede626d441bacdf28a825819fa9ea0505df12c43f2950ff7f2b5ba600","stark_r":"0x59eeb83d120698a6d0606f0ad91b635d7087d6bd0843934244285d58b8b1b9f","stark_s":"0x350f1101406ddae1ba9d90cc282bbc99c24ac5a09d403c50334427e42dd5909","stark_pk":"0x4d54d72263f75f14c4fd62a038b3e63d72f04ca55c5fc261224659f8525d058"},"trace":{"BTC/USD@binance_us":"19915.12","BTC/USD@bitstamp":"19904","BTC/USD@coinbasepro":"19913.64","BTC/USD@ftx":"19908","BTC/USD@gemini":"19905.41","BTC/USD@kraken":"19912.2"}}]
