[{"price":{"wat":"MANAUSD","val":"684600000000000000","age":1665434966,"v":"1b","r":"941a56e25c77f03edec465ae0641438ef2a9aeca84c9a05151fbe1ef67f117d7","s":"4ddbf27173446bfc96b6f7503798f0adfa6b243dd278bd5da0166fed23b0c422","stark_r":"0x0","stark_s":"0x0","stark_pk":"0x0"},"trace":{"BTC/USD@binance_us":"19239","BTC/USD@bitstamp":"19235","BTC/USD@coinbasepro":"19237.79","BTC/USD@ftx":"19231","BTC/USD@gemini":"19227.96","BTC/USD@kraken":"19230.4","BTC/USDT@binance":"19239.67","BTC/USDT@okx":"19239.9","KRW/USD@openexchangerates":"0.0007","MANA/BTC@binance":"3.559e-05","MANA/KRW@upbit":"978","MANA/USD@binance_us":"0.6847","MANA/USD@coinbasepro":"0.6845","MANA/USD@ftx":"0.6845","MANA/USD@kraken":"0.68471","MANA/USDT@okx":"0.6847","USDT/USD@bitfinex":"1.0001","USDT/USD@coinbasepro":"0.99993","USDT/USD@ftx":"1","USDT/USD@kraken":"0.9999"}},{"price":{"wat":"ETHBTC","val":"67992500000000010","age":1665434971,"v":"1b","r":"97763f3c03c0864539532d4792d7c5441ff9746a4ae9c712491cce926a32c4c7","s":"39aaf469375d11a59d75291dd5a79ef76c619e2a315e871322655d21f8c7dcd3","stark_r":"0x65ee2fbcad2a897cc21ed0091d834ab5b2dd463a5e8485fb8127d8e0b282f29","stark_s":"0x5704ecca7958b8169a7cfc0b1e099e029510c75727d6b6a918b81bafc30313d","stark_pk":"0x2dacd0e8df86be8df0b2bc5fcecb9ac14fa640fc4caf87efe5de013c44faeac"},"trace":{"ETH/BTC@binance":"0.067985","ETH/BTC@bitfinex":"0.067972","ETH/BTC@coinbasepro":"0.068","ETH/BTC@huobi":"0.067983","ETH/BTC@kraken":"0.06801","ETH/BTC@poloniex":"0.068"}},{"price":{"wat":"BTCUSD","val":"19242595000000000000000","age":1665434967,"v":"1c","r":"4f2c52f45d8a9d8634c4c8fff667a77a876e68c7d185f2b0901280690d1da3b2","s":"6d25ad27eb0d57c9e938598bf5c751a84ef9651e3ebf9a8a13b86b01f9fdf035","stark_r":"0x0","stark_s":"0x0","stark_pk":"0x0"},"trace":{"BTC/USD@binance_us":"19246.44","BTC/USD@bitstamp":"19241","BTC/USD@coinbasepro":"19243.59","BTC/USD@ftx":"19236","BTC/USD@gemini":"19247.78","BTC/USD@kraken":"19241.6"}},{"price":{"wat":"ETHBTC","val":"67992500000000010","age":1665434977,"v":"1b","r":"75c35d5f834bdb6264c6c46a4cbdbfd168325cb2eaf269e9142a0fb25c242564","s":"2300396e5f0dd6e21165eaa3e4f03c2d75dd4e34cd978c515e69a8ef2a765d3f","stark_r":"0x0","stark_s":"0x0","stark_pk":"0x0"},"trace":{"ETH/BTC@binance":"0.067985","ETH/BTC@bitfinex":"0.067972","ETH/BTC@coinbasepro":"0.068","ETH/BTC@huobi":"0.067983","ETH/BTC@kraken":"0.06801","ETH/BTC@poloniex":"0.068"}},{"price":{"wat":"MATICUSD","val":"837263348586694700","age":1665434970,"v":"1b","r":"c6581b690d46c01e67a27ccf79c9cb292e4484cc24e841dd1558fbc12c68c8d8","s":"50141fca1b443cf84888699278d054b075e13c521865e48a396fee2facb8a5fc","stark_r":"0x0","stark_s":"0x0","stark_pk":"0x0"},"trace":{"BTC/USD@binance_us":"19246.44","BTC/USD@bitstamp":"19241","BTC/USD@coinbasepro":"19243.24","BTC/USD@ftx":"19236","BTC/USD@gemini":"19247.78","BTC/USD@kraken":"19241.6","BTC/USDT@binance":"19244.25","BTC/USDT@okx":"19246.1","MATIC/USD@coinbasepro":"0.8374","MATIC/USD@ftx":"0.837","MATIC/USD@gemini":"0.8366","MATIC/USD@kraken":"0.8373","MATIC/USDT@binance":"0.8373","MATIC/USDT@huobi":"0.8374735","USDT/USD@bitfinex":"1.0001","USDT/USD@coinbasepro":"0.99992","USDT/USD@ftx":"1","USDT/USD@kraken":"0.9999"}},{"price":{"wat":"YFIUSD","val":"7986970000000000000000","age":1665434967,"v":"1b","r":"1c0b29812a7af0a0b776a1cbb079d0e5cb26fbff499eb3a74db7a05c8d2d0e07","s":"1a728ed94ff3334d54a7b78c89b75bbeca509544004ef5eb9a3fa6b509b8621c","stark_r":"0x6281ce5503d8a3a9f34415ed6d183590e016bc689402fadc57dfe53c8fe45c5","stark_s":"0x1fa50d6234e04ab778973f18db79fd7251bda2806107e87ec7889d13bdea239","stark_pk":"0x2dacd0e8df86be8df0b2bc5fcecb9ac14fa640fc4caf87efe5de013c44faeac"},"trace":{"BTC/USD@binance_us":"19246.44","BTC/USD@bitstamp":"19241","BTC/USD@coinbasepro":"19242.91","BTC/USD@ftx":"19236","BTC/USD@gemini":"19247.78","BTC/USD@kraken":"19241.6","BTC/USDT@binance":"19244.15","BTC/USDT@okx":"19246.1","ETH/BTC@binance":"0.067985","ETH/USD@bitstamp":"1308.2","ETH/USD@coinbasepro":"1308.29","ETH/USD@ftx":"1307.9","ETH/USD@gemini":"1308.49","ETH/USD@kraken":"1308.27","ETH/USD@uniswapV3":"1307.7578514598033","ETH/YFI@balancerV2":"0.16472135338833585","USDT/USD@bitfinex":"1.0001","USDT/USD@coinbasepro":"0.99992","USDT/USD@ftx":"1","USDT/USD@kraken":"0.9999","YFI/ETH@sushiswap":"6.113554887838911","YFI/USD@coinbasepro":"7986.97","YFI/USD@ftx":"7975","YFI/USD@kraken":"7987","YFI/USDT@binance":"7976","YFI/USDT@okx":"7991"}},{"price":{"wat":"MATICUSD","val":"837098980150000000","age":1665434978,"v":"1b","r":"60375334eaa6659b23898bec116b7ad76c36751eabcbc75fc0796aceb082e1c8","s":"10b0f23bc3af2248ce76394ba995122c0bf48bc66c5ebc1cbd38b9ab1d85dae4","stark_r":"0x0","stark_s":"0x0","stark_pk":"0x0"},"trace":{"maticusd@binance":"0.8370759609","maticusd@coinbase":"0.8371000000","maticusd@ftx":"0.8368000000","maticusd@gemini":"0.8375500000","maticusd@huobi":"0.8370979603","maticusd@kraken":"0.8375000000"}},{"price":{"wat":"MANAUSD","val":"684665000000000000","age":1665434978,"v":"1b","r":"48a87dcf04e8fab63e31f4dc7e99a565f055f3e4f2dc12c186550985b3c4d099","s":"764ae04df1cb630f5c32eefd3ded828396c34bce7889c94fbef18a2312d33a44","stark_r":"0x0","stark_s":"0x0","stark_pk":"0x0"},"trace":{"BTC/USD@binance_us":"19246.44","BTC/USD@bitstamp":"19241","BTC/USD@coinbasepro":"19243.59","BTC/USD@ftx":"19236","BTC/USD@gemini":"19247.78","BTC/USD@kraken":"19241.6","BTC/USDT@binance":"19245.23","BTC/USDT@okx":"19246.2","MANA/BTC@binance":"3.559e-05","MANA/KRW@upbit":"979","MANA/USD@binance_us":"0.6847","MANA/USD@coinbasepro":"0.6846","MANA/USD@ftx":"0.6845","MANA/USD@kraken":"0.68463","MANA/USDT@okx":"0.6849","USDT/USD@bitfinex":"1.0001","USDT/USD@coinbasepro":"0.99992","USDT/USD@ftx":"1","USDT/USD@kraken":"0.9999"}},{"price":{"wat":"WSTETHUSD","val":"1416889210501800800000","age":1665434970,"v":"1b","r":"f15eec6a2c7c11ba5c31746cec2d10e58bb9e05bfd45378cfb8a85670442afb7","s":"4ebafd203ef3cbf080ec8a0cabc25833f3ce65ab8c113b01eded61674e2d1ea7","stark_r":"0x0","stark_s":"0x0","stark_pk":"0x0"},"trace":{"BTC/USD@binance_us":"19240.58","BTC/USD@bitstamp":"19235","BTC/USD@coinbasepro":"19241.51","BTC/USD@ftx":"19230","BTC/USD@gemini":"19245.65","BTC/USD@kraken":"19231.1","ETH/BTC@binance":"0.067984","ETH/USD@bitstamp":"1307.4","ETH/USD@coinbasepro":"1308.21","ETH/USD@ftx":"1307.3","ETH/USD@gemini":"1307.68","ETH/USD@kraken":"1307.52","ETH/USD@uniswapV3":"1307.7576321854012","STETH/ETH@balancerV2":"0.9945150973089191","STETH/ETH@curve":"0.9942577174747437","WSTETH/STETH@wsteth":"1.0896304531466714"}},{"price":{"wat":"MATICUSD","val":"837095443250000000","age":1665434977,"v":"1c","r":"9fe6e8360ffc58f2b3cd4219bed3a01982a9d2e5fd7d50dac44ea594f55f1fdd","s":"3f50728764590e4b5aa103831613f39236e79eb95fa3244204d8a980e54082cf","stark_r":"0x0","stark_s":"0x0","stark_pk":"0x0"},"trace":{"maticusd@binance":"0.8370748870","maticusd@coinbase":"0.8371000000","maticusd@ftx":"0.8368000000","maticusd@gemini":"0.8375500000","maticusd@huobi":"0.8370908865","maticusd@kraken":"0.8375000000"}},{"price":{"wat":"MATICUSD","val":"837085514500000000","age":1665434971,"v":"1c","r":"22fc2fb34cedcd9cb76f5cb9afbcea6d6d58028aac353d7d133d8cd57638964c","s":"70b42f3344d728855330e0facbb18b5ebcc4bf1451b5730863677a07b117f510","stark_r":"0x0","stark_s":"0x0","stark_pk":"0x0"},"trace":{"maticusd@binance":"0.8370330320","maticusd@coinbase":"0.8371000000","maticusd@ftx":"0.8368000000","maticusd@gemini":"0.8375200000","maticusd@huobi":"0.8370710290","maticusd@kraken":"0.8375000000"}},{"price":{"wat":"FILUSD","val":"5288000000000000000","age":1665434966,"v":"1c","r":"5bc4bc62a13e7c2c3d02b321922a1f87ec7ef655cd0497e105bcb14f2437e541","s":"46830abd4a01eef34c457a8dc88c33a3bc4677e8204f0aef88927a4719ee37b9","stark_r":"0x10fd0b439109036285cb51f80a1f73f0b61626e090404b6cd3ed9816980ca5d","stark_s":"0x1ddbcb4ab322edc5abefe00c6ff9013056b3edf248e76312282a33461f1aa5a","stark_pk":"0x26cd35ce61b798e2e80d1d4d1f7d3f40f60dd19f2533e557808c1f5675471e9"},"trace":{"binance":"5.2797360000","coinbase":"5.2880000000","gemini":"5.2883000000","huobi":"5.2892355250","kraken":"5.2880000000"}},{"price":{"wat":"MANAUSD","val":"684615000000000000","age":1665434974,"v":"1b","r":"200430120ff97ab90bc5ec26b687223da23910b26fc12b9ec1d3e9bfac780657","s":"6986ea4a225f578ab2be7f632d35252ba033b0c3ced9241e53d2f982f7f06dc0","stark_r":"0x0","stark_s":"0x0","stark_pk":"0x0"},"trace":{"manausd@binance":"0.6844452400","manausd@binance_us":"0.6847000000","manausd@coinbase":"0.6846000000","manausd@ftx":"0.6845000000","manausd@kraken":"0.6846300000","manausd@okx":"0.6848452080"}},{"price":{"wat":"MATICUSD","val":"837257692892500100","age":1665434979,"v":"1b","r":"bc823b564db00a49842a983096ef5f8242b813ffb09e0bc775c4bde2361cfc52","s":"68f355a3f2663b79c106dac29ff462366c73a2a13975b89140bfad1432a34efc","stark_r":"0x0","stark_s":"0x0","stark_pk":"0x0"},"trace":{"BTC/USD@binance_us":"19237.31","BTC/USD@bitstamp":"19239","BTC/USD@coinbasepro":"19243.73","BTC/USD@ftx":"19236","BTC/USD@gemini":"19243.99","BTC/USD@kraken":"19237.8","BTC/USDT@binance":"19240.46","BTC/USDT@okx":"19243.8","MATIC/USD@coinbasepro":"0.8374","MATIC/USD@ftx":"0.8368","MATIC/USD@gemini":"0.83755","MATIC/USD@kraken":"0.8375","MATIC/USDT@binance":"0.8371","MATIC/USDT@huobi":"0.8371405000000001","USDT/USD@bitfinex":"1","USDT/USD@coinbasepro":"0.99994","USDT/USD@ftx":"1","USDT/USD@kraken":"1"}},{"price":{"wat":"MANAUSD","val":"684700000000000000","age":1665434972,"v":"1c","r":"9e37b2f391cb8d8c8f4122cea8e0447f7c865e743e236ed675f4f1e8db3d9362","s":"2a651d159b6a62b38a6b96ed6c4703c64868f801d45c63259b60c40fb990474a","stark_r":"0x0","stark_s":"0x0","stark_pk":"0x0"},"trace":{"BTC/USD@binance_us":"19240.58","BTC/USD@bitstamp":"19235","BTC/USD@coinbasepro":"19243.47","BTC/USD@ftx":"19236","BTC/USD@gemini":"19245.65","BTC/USD@kraken":"19231.1","BTC/USDT@binance":"19242.75","BTC/USDT@okx":"19246.2","KRW/USD@openexchangerates":"0.0007","MANA/BTC@binance":"3.559e-05","MANA/KRW@upbit":"979","MANA/USD@binance_us":"0.6847","MANA/USD@coinbasepro":"0.6846","MANA/USD@ftx":"0.6845","MANA/USD@kraken":"0.68471","MANA/USDT@okx":"0.6849","USDT/USD@bitfinex":"1.0001","USDT/USD@coinbasepro":"0.99994","USDT/USD@ftx":"1","USDT/USD@kraken":"0.9999"}},{"price":{"wat":"MATICUSD","val":"837102257250000000","age":1665434974,"v":"1c","r":"114555c02df0c87a324f115051fae2e8d3264b98ad82c8c35bcfbbb5d4c82ef8","s":"32c8bb6cedc7123d74a2001d72ff9093775df85c2cbe4d1b45678d1fa83d931d","stark_r":"0x0","stark_s":"0x0","stark_pk":"0x0"},"trace":{"maticusd@binance":"0.8370665160","maticusd@coinbase":"0.8371000000","maticusd@ftx":"0.8368000000","maticusd@gemini":"0.8375200000","maticusd@huobi":"0.8371045145","maticusd@kraken":"0.8375000000"}},{"price":{"wat":"WSTETHUSD","val":"1417452637631879000000","age":1665434971,"v":"1b","r":"9cfab724f9d4d0bf2549de5297583da26ef9afd433e2cf6a6c35b21561d37677","s":"209a9f208716a373e18cd13c879b469f470555909bb9f3c819ddcecc972825ce","stark_r":"0x0","stark_s":"0x0","stark_pk":"0x0"},"trace":{"BTC/USD@binance_us":"19246.44","BTC/USD@bitstamp":"19241","BTC/USD@coinbasepro":"19243.59","BTC/USD@ftx":"19236","BTC/USD@gemini":"19247.78","BTC/USD@kraken":"19241.6","ETH/BTC@binance":"0.067984","ETH/USD@bitstamp":"1308.2","ETH/USD@coinbasepro":"1308.42","ETH/USD@ftx":"1307.9","ETH/USD@gemini":"1308.49","ETH/USD@kraken":"1308.27","ETH/USD@uniswapV3":"1307.7578514598033","STETH/ETH@balancerV2":"0.9945150973089191","STETH/ETH@curve":"0.9942577174747437","WSTETH/STETH@wsteth":"1.0896304531466714"}},{"price":{"wat":"WSTETHUSD","val":"1416640100878500000000","age":1665434960,"v":"1c","r":"2b3fa88fef61d82b86d924e87827c03e426bd900dc047ccc072ec05f37850d97","s":"477470b40beae465cebe6c22a172c9175221811c737679d8839521aa2e5505f7","stark_r":"0x0","stark_s":"0x0","stark_pk":"0x0"},"trace":{"wstethusd@balancer_v2":"1416.8233387539","wstethusd@curve":"1416.4568630031"}},{"price":{"wat":"MATICUSD","val":"837087443500000000","age":1665434968,"v":"1c","r":"d46d756372e3fd3cebda147c6e7d8d0d4e3cf42acb0fec4e38e0d5d7ac763432","s":"5b2c65c0550730224d7fc96c11317bfdebd761c2e996058761e4293f5e665496","stark_r":"0x3484c638ae3d57dbc4fc230a015a3943a0124f3ee57f15d6ca8a44fa5d64542","stark_s":"0x51ff5b4cd108f544612740c5921195bd709f400e9c73c04542f14fac505ab52","stark_pk":"0x4d54d72263f75f14c4fd62a038b3e63d72f04ca55c5fc261224659f8525d058"},"trace":{"maticusd@binance":"0.8370748870","maticusd@coinbase":"0.8371000000","maticusd@ftx":"0.8368000000","maticusd@gemini":"0.8375200000","maticusd@huobi":"0.8370598875","maticusd@kraken":"0.8375000000"}},{"price":{"wat":"LINKUSD","val":"7690000000000000000","age":1665434967,"v":"1b","r":"a97b4494bc898050b1a5ebbc0e074f1407de48478e1fdf164fceddbbd5e2c987","s":"26fedef37e815114b118ddfa67611738c0504299e971b2e75535ec1b3e621fcb","stark_r":"0x0","stark_s":"0x0","stark_pk":"0x0"},"trace":{"BTC/USD@binance_us":"19240.58","BTC/USD@bitstamp":"19235","BTC/USD@coinbasepro":"19243.47","BTC/USD@ftx":"19236","BTC/USD@gemini":"19245.65","BTC/USD@kraken":"19231.1","ETH/BTC@binance":"0.067985","ETH/USD@bitstamp":"1307.4","ETH/USD@coinbasepro":"1308.14","ETH/USD@ftx":"1307.8","ETH/USD@gemini":"1308.49","ETH/USD@kraken":"1307.52","ETH/USD@uniswapV3":"1307.7578514598033","LINK/BTC@binance":"0.0003998","LINK/ETH@uniswapV3":"0.005869563161017921","LINK/USD@bitstamp":"7.68","LINK/USD@coinbasepro":"7.69","LINK/USD@ftx":"7.6935","LINK/USD@gemini":"7.68","LINK/USD@kraken":"7.69081"}},{"price":{"wat":"ETHUSD","val":"1308200000000000000000","age":1665434975,"v":"1b","r":"bf799c13121a5ea9e8dab5dbfa8c4e1f7e1b6b9ea978a42aa40ce2d32686e0c9","s":"7525ca94b22d946de4f5f71267a06573b86a2d3e3bec6178921698ae4d4ad951","stark_r":"0x4134f2a5b402383e777c7c8515c61d4d7b97fcbb3c8221e384ff9b52de6fda4","stark_s":"0x688ffe5c772e2a973134df9416f6f01bc693bad2df7abfba78ac30728496ee9","stark_pk":"0x2dacd0e8df86be8df0b2bc5fcecb9ac14fa640fc4caf87efe5de013c44faeac"},"trace":{"BTC/USD@binance_us":"19246.44","BTC/USD@bitstamp":"19241","BTC/USD@coinbasepro":"19242.91","BTC/USD@ftx":"19236","BTC/USD@gemini":"19247.78","BTC/USD@kraken":"19241.6","ETH/BTC@binance":"0.067985","ETH/USD@bitstamp":"1308.2","ETH/USD@coinbasepro":"1308.29","ETH/USD@ftx":"1307.9","ETH/USD@gemini":"1308.49","ETH/USD@kraken":"1308.27","ETH/USD@uniswapV3":"1307.7578514598033"}},{"price":{"wat":"AAVEUSD","val":"74758308480000000000","age":1665434973,"v":"1c","r":"c046414f09b6eee9c88ce80716100ca2f61a76f50d36adb405f72d79afed3b0d","s":"1325e7b0d575d817473ecc6295154f8f696ede89ef291481dcab93ecca82c6f7","stark_r":"0x73c3218762dab3174b82bfa065b7d71f05e3b688e1c8dcb3640cfcc79a16c8b","stark_s":"0x3441bef149c74b3fcff40b2aee9fd277aa02e1e0b3b50b0d23a135aff5eb2b9","stark_pk":"0x26cd35ce61b798e2e80d1d4d1f7d3f40f60dd19f2533e557808c1f5675471e9"},"trace":{"balancer":"75.4846831398","binance":"74.7583084800","gemini":"74.8025000000","huobi":"74.7450625600","uniswap":"74.2396840577"}},{"price":{"wat":"MANAUSD","val":"684686473050000000","age":1665434978,"v":"1b","r":"67e533eff9a1b2e04a511a40ae7c9bf6c2ffc4b51c924270430e32cb9c960e85","s":"50252c57d6bdba2ebb4ede70f4d6b3751c21b1d4d7474726b47203f6b1f0c92d","stark_r":"0x0","stark_s":"0x0","stark_pk":"0x0"},"trace":{"BTC/USD@binance_us":"19240.58","BTC/USD@bitstamp":"19235","BTC/USD@coinbasepro":"19241.51","BTC/USD@ftx":"19230","BTC/USD@gemini":"19245.65","BTC/USD@kraken":"19231.1","BTC/USDT@binance":"19242.64","BTC/USDT@okx":"19245.8","MANA/BTC@binance":"3.559e-05","MANA/KRW@upbit":"979","MANA/USD@binance_us":"0.6847","MANA/USD@coinbasepro":"0.6845","MANA/USD@ftx":"0.6845","MANA/USD@kraken":"0.68471","MANA/USDT@okx":"0.685","USDT/USD@bitfinex":"1.0001","USDT/USD@coinbasepro":"0.99992","USDT/USD@ftx":"1","USDT/USD@kraken":"0.9999"}},{"price":{"wat":"YFIUSD","val":"7986970000000000000000","age":1665434973,"v":"1b","r":"7f3f00da71c9a454ababa9bc6cad54bb0b057eacdaead9eb338a0fcadb6fa7e7","s":"7d258472ad45fe0bef8c1960e37826061e53220702259a75faa811f328d86076","stark_r":"0x0","stark_s":"0x0","stark_pk":"0x0"},"trace":{"BTC/USD@binance_us":"19246.44","BTC/USD@bitstamp":"19241","BTC/USD@coinbasepro":"19243.24","BTC/USD@ftx":"19236","BTC/USD@gemini":"19247.78","BTC/USD@kraken":"19241.6","BTC/USDT@binance":"19244.25","BTC/USDT@okx":"19246.1","ETH/BTC@binance":"0.067985","ETH/USD@bitstamp":"1308.2","ETH/USD@coinbasepro":"1308.29","ETH/USD@ftx":"1307.9","ETH/USD@gemini":"1308.49","ETH/USD@kraken":"1308.27","ETH/USD@uniswapV3":"1307.7578514598033","ETH/YFI@balancerV2":"0.16472135338833585","USDT/USD@bitfinex":"1.0001","USDT/USD@coinbasepro":"0.99992","USDT/USD@ftx":"1","USDT/USD@kraken":"0.9999","YFI/ETH@sushiswap":"6.113554887838911","YFI/USD@coinbasepro":"7986.97","YFI/USD@ftx":"7975","YFI/USD@kraken":"7987","YFI/USDT@binance":"7976","YFI/USDT@okx":"7991"}},{"price":{"wat":"YFIUSD","val":"7986970000000000000000","age":1665434972,"v":"1b","r":"693ecda954b99e8a1ca1c8c4a816350eeb72272011e8706ed3fbf1d198093ecb","s":"16220d9ddb1a773c17af9c2f759cfd1de75d509cdbb187186f8399c19c5846b4","stark_r":"0x4c716ed85b1074ed3a581b6c7eea31b61839192145559789796341734175e50","stark_s":"0x5f8ec2f66c959e64323fabfcd931e5ebe147cbb640c24328a1ee70e9ddd32b4","stark_pk":"0x4d54d72263f75f14c4fd62a038b3e63d72f04ca55c5fc261224659f8525d058"},"trace":{"yfiusd@balancer_v2":"7940.4676091011","yfiusd@binance":"7975.7607200000","yfiusd@coinbase":"7986.9700000000","yfiusd@ftx":"7975.0000000000","yfiusd@kraken":"7987.0000000000","yfiusd@okx":"7990.7602700000","yfiusd@sushiswap":"7996.3131987155"}},{"price":{"wat":"LINKUSD","val":"7685000000000000000","age":1665434968,"v":"1b","r":"d99221a1186f45a8378e0abbbc9660819cc204f85adbd2b0df50d4fc77c0d92a","s":"18fe2844b2a875ab43789321ccfa814f13db44f0ecc4bf6eb07525ccbfab9abe","stark_r":"0x0","stark_s":"0x0","stark_pk":"0x0"},"trace":{"linkusd@binance":"7.6893848000","linkusd@bitstamp":"7.6800000000","linkusd@coinbase":"7.6850000000","linkusd@ftx":"7.6935000000","linkusd@gemini":"7.6800000000","linkusd@kraken":"7.6908100000","linkusd@uniswap_v3":"7.6785625782"}},{"price":{"wat":"MATICUSD","val":"837087443500000000","age":1665434974,"v":"1c","r":"8e10d16db0e0cb4aac4bfbcbc15504ccdb8d5d48b558c0e59d72b2eb6eb38dc4","s":"6d588fb78eeea3c28d573016e445162bbf812934b2c3a31659a1a3aaa74096b1","stark_r":"0x0","stark_s":"0x0","stark_pk":"0x0"},"trace":{"maticusd@binance":"0.8370748870","maticusd@coinbase":"0.8371000000","maticusd@ftx":"0.8368000000","maticusd@gemini":"0.8375200000","maticusd@huobi":"0.8370488878","maticusd@kraken":"0.8375000000"}},{"price":{"wat":"MATICUSD","val":"837312317000000100","age":1665434980,"v":"1c","r":"79ee238878a26c9ff0cfba88ec2cc7908f41baabc81da12cff6fe209df18d9ac","s":"0b46510e12b25832bcd2c6da1a2f1d4876825af10bafcdfa8c99ddb8c37fe67b","stark_r":"0x0","stark_s":"0x0","stark_pk":"0x0"},"trace":{"BTC/USD@binance_us":"19246.44","BTC/USD@bitstamp":"19235","BTC/USD@coinbasepro":"19243.63","BTC/USD@ftx":"19236","BTC/USD@gemini":"19247.78","BTC/USD@kraken":"19232.4","BTC/USDT@binance":"19245.44","BTC/USDT@okx":"19246.2","MATIC/USD@coinbasepro":"0.8374","MATIC/USD@ftx":"0.837","MATIC/USD@gemini":"0.8366","MATIC/USD@kraken":"0.8373","MATIC/USDT@binance":"0.8374","MATIC/USDT@huobi":"0.8374185000000001","USDT/USD@bitfinex":"1.0001","USDT/USD@coinbasepro":"0.99992","USDT/USD@ftx":"1","USDT/USD@kraken":"0.9999"}},{"price":{"wat":"LINKUSD","val":"7689000000000000000","age":1665434974,"v":"1c","r":"f7a3601b842998725db4c7ba47e2a4d4f2a412a1d69fd14a67fea7bd13b31fc6","s":"37717085ddc45c2516159b2da65ec4e98dd593d1523462a6be92a180bcb1cfef","stark_r":"0x0","stark_s":"0x0","stark_pk":"0x0"},"trace":{"BTC/USD@binance_us":"19246.44","BTC/USD@bitstamp":"19241","BTC/USD@coinbasepro":"19243.59","BTC/USD@ftx":"19236","BTC/USD@gemini":"19247.78","BTC/USD@kraken":"19241.6","ETH/BTC@binance":"0.067984","ETH/USD@bitstamp":"1308.2","ETH/USD@coinbasepro":"1308.42","ETH/USD@ftx":"1307.9","ETH/USD@gemini":"1308.49","ETH/USD@kraken":"1308.27","ETH/USD@uniswapV3":"1307.7578514598033","LINK/BTC@binance":"0.0003998","LINK/ETH@uniswapV3":"0.005869563161017921","LINK/USD@bitstamp":"7.68","LINK/USD@coinbasepro":"7.689","LINK/USD@ftx":"7.6935","LINK/USD@gemini":"7.68","LINK/USD@kraken":"7.69081"}},{"price":{"wat":"MANAUSD","val":"684700000000000000","age":1665434970,"v":"1b","r":"2b2daf4a07c7f06b6335edc8812d1ee5cdb92733c866486b3ce0d6a0016b37ad","s":"5f1f05548e29052000bf1046e733824bff4607f03db3e4a0577d4bbaa57e8d84","stark_r":"0x0","stark_s":"0x0","stark_pk":"0x0"},"trace":{"BTC/USD@binance_us":"19241.95","BTC/USD@bitstamp":"19241","BTC/USD@coinbasepro":"19242.11","BTC/USD@ftx":"19237","BTC/USD@gemini":"19247.78","BTC/USD@kraken":"19241.6","BTC/USDT@binance":"19243.11","BTC/USDT@okx":"19246.1","KRW/USD@openexchangerates":"0.0007","MANA/BTC@binance":"3.559e-05","MANA/KRW@upbit":"979","MANA/USD@binance_us":"0.6847","MANA/USD@coinbasepro":"0.6845","MANA/USD@ftx":"0.6845","MANA/USD@kraken":"0.68463","MANA/USDT@okx":"0.6849","USDT/USD@bitfinex":"1.0001","USDT/USD@coinbasepro":"0.99993","USDT/USD@ftx":"1","USDT/USD@kraken":"0.9999"}},{"price":{"wat":"LINKUSD","val":"7690000000000000000","age":1665434974,"v":"1c","r":"7b9542b2b7940047d88c6d80da9986bad8784ef2e6862971d82ca6bf95f7e9d7","s":"51a06f88b92fb73e920d507c4662461aa104435fa96e3a363585b8f5d1fff555","stark_r":"0x0","stark_s":"0x0","stark_pk":"0x0"},"trace":{"BTC/USD@binance_us":"19240.58","BTC/USD@bitstamp":"19235","BTC/USD@coinbasepro":"19241.51","BTC/USD@ftx":"19230","BTC/USD@gemini":"19245.65","BTC/USD@kraken":"19231.1","ETH/BTC@binance":"0.067984","ETH/USD@bitstamp":"1307.4","ETH/USD@coinbasepro":"1308.21","ETH/USD@ftx":"1307.3","ETH/USD@gemini":"1307.68","ETH/USD@kraken":"1307.52","ETH/USD@uniswapV3":"1307.7576321854012","LINK/BTC@binance":"0.0003998","LINK/ETH@uniswapV3":"0.005869563161017921","LINK/USD@bitstamp":"7.68","LINK/USD@coinbasepro":"7.69","LINK/USD@ftx":"7.6935","LINK/USD@gemini":"7.68","LINK/USD@kraken":"7.69081"}}]
